.gitignore
MANIFEST.in
setup.py
ebs/__init__.py
ebs/linuxnode/__init__.py
ebs/linuxnode/gui/__init__.py
ebs/linuxnode/gui/kivy/__init__.py
ebs/linuxnode/gui/kivy/tables/__init__.py
ebs/linuxnode/gui/kivy/tables/animated.py
ebs/linuxnode/gui/kivy/tables/renderable.py
ebs/linuxnode/gui/kivy/timetable/__init__.py
ebs/linuxnode/gui/kivy/timetable/base.py
ebs/linuxnode/tables/__init__.py
ebs/linuxnode/tables/basic.py
ebs/linuxnode/tables/spec.py
ebs/linuxnode/tables/translatable.py
ebs/linuxnode/timetable/__init__.py
ebs_linuxnode_tables.egg-info/PKG-INFO
ebs_linuxnode_tables.egg-info/SOURCES.txt
ebs_linuxnode_tables.egg-info/dependency_links.txt
ebs_linuxnode_tables.egg-info/requires.txt
ebs_linuxnode_tables.egg-info/top_level.txt